Workbook

Sheet Operaciones
A1: ID_Operación | B1: Fecha | C1: Cliente | D1: Código Producto | E1: País Destino | F1: Unidades | G1: Precio FOB | H1: Costo Unitario | I1: Estado | J1: Producto | K1: Categoría | L1: Región | M1: Arancel % | N1: Clasificación mercado | O1: Valor FOB | P1: Costo total | Q1: Utilidad | R1: Margen | S1: Nivel rentabilidad | T1: Nivel de operación | U1: Prioridad comercial
A2: EX001 | B2: 46027 | C2: Comercial Maya | D2: P003 | E2: Guatemala | F2: 850 | G2: 4.8 | H2: 3.2 | I2: Embarcado | J2: =VLOOKUP(D2,Productos!$A$2:$D$6,2,FALSE()) -> Miel natural | K2: =VLOOKUP(D2,Productos!$A$2:$D$6,3,FALSE()) -> Apícola | L2: =VLOOKUP(E2,Mercados!$A$2:$D$7,2,FALSE()) -> Centroamérica | M2: =VLOOKUP(E2,Mercados!$A$2:$D$7,3,FALSE()) -> 0.03 | N2: =VLOOKUP(E2,Mercados!$A$2:$D$7,4,FALSE()) -> Estratégico | O2: =F2*G2 -> 4080 | P2: =F2*H2 -> 2720 | Q2: =O2-P2 -> 1360 | R2: =Q2/O2 -> 0.33333333 | S2: =IF(R2>=30%,"Alta",IF(R2>=15%,"Media","Baja")) -> Alta | T2: =IF(O2>=10000,"Grande",IF(O2>=5000,"Mediana","Pequeña")) -> Pequeña | U2: =IF(AND(N2="Estratégico",R2>=30%),"Alta",IF(OR(AND(N2="Estratégico",R2<30%),AND(N2="Potencial",R2>=30%)),"Media","Baja")) -> Alta
A3: EX002 | B3: 46034 | C3: Global Foods | D3: P001 | E3: EE.UU. | F3: 1200 | G3: 6.5 | H3: 4.1 | I3: Entregado | J3: =VLOOKUP(D3,Productos!$A$2:$D$6,2,FALSE()) -> Café especial | K3: =VLOOKUP(D3,Productos!$A$2:$D$6,3,FALSE()) -> Café | L3: =VLOOKUP(E3,Mercados!$A$2:$D$7,2,FALSE()) -> Norteamérica | M3: =VLOOKUP(E3,Mercados!$A$2:$D$7,3,FALSE()) -> 0.05 | N3: =VLOOKUP(E3,Mercados!$A$2:$D$7,4,FALSE()) -> Estratégico | O3: =F3*G3 -> 7800 | P3: =F3*H3 -> 4920 | Q3: =O3-P3 -> 2880 | R3: =Q3/O3 -> 0.36923077 | S3: =IF(R3>=30%,"Alta",IF(R3>=15%,"Media","Baja")) -> Alta | T3: =IF(O3>=10000,"Grande",IF(O3>=5000,"Mediana","Pequeña")) -> Mediana | U3: =IF(AND(N3="Estratégico",R3>=30%),"Alta",IF(OR(AND(N3="Estratégico",R3<30%),AND(N3="Potencial",R3>=30%)),"Media","Baja")) -> Alta
A4: EX003 | B4: 46042 | C4: Distribuidora Tica | D4: P004 | E4: Costa Rica | F4: 650 | G4: 8.2 | H4: 5.9 | I4: Embarcado | J4: =VLOOKUP(D4,Productos!$A$2:$D$6,2,FALSE()) -> Maní procesado | K4: =VLOOKUP(D4,Productos!$A$2:$D$6,3,FALSE()) -> Semillas | L4: =VLOOKUP(E4,Mercados!$A$2:$D$7,2,FALSE()) -> Centroamérica | M4: =VLOOKUP(E4,Mercados!$A$2:$D$7,3,FALSE()) -> 0.02 | N4: =VLOOKUP(E4,Mercados!$A$2:$D$7,4,FALSE()) -> Estratégico | O4: =F4*G4 -> 5330 | P4: =F4*H4 -> 3835 | Q4: =O4-P4 -> 1495 | R4: =Q4/O4 -> 0.2804878 | S4: =IF(R4>=30%,"Alta",IF(R4>=15%,"Media","Baja")) -> Media | T4: =IF(O4>=10000,"Grande",IF(O4>=5000,"Mediana","Pequeña")) -> Mediana | U4: =IF(AND(N4="Estratégico",R4>=30%),"Alta",IF(OR(AND(N4="Estratégico",R4<30%),AND(N4="Potencial",R4>=30%)),"Media","Baja")) -> Media
A5: EX004 | B5: 46056 | C5: Iberia Foods | D5: P002 | E5: España | F5: 950 | G5: 7.1 | H5: 4.8 | I5: Pendiente | J5: =VLOOKUP(D5,Productos!$A$2:$D$6,2,FALSE()) -> Cacao en grano | K5: =VLOOKUP(D5,Productos!$A$2:$D$6,3,FALSE()) -> Cacao | L5: =VLOOKUP(E5,Mercados!$A$2:$D$7,2,FALSE()) -> Europa | M5: =VLOOKUP(E5,Mercados!$A$2:$D$7,3,FALSE()) -> 0.1 | N5: =VLOOKUP(E5,Mercados!$A$2:$D$7,4,FALSE()) -> Potencial | O5: =F5*G5 -> 6745 | P5: =F5*H5 -> 4560 | Q5: =O5-P5 -> 2185 | R5: =Q5/O5 -> 0.32394366 | S5: =IF(R5>=30%,"Alta",IF(R5>=15%,"Media","Baja")) -> Alta | T5: =IF(O5>=10000,"Grande",IF(O5>=5000,"Mediana","Pequeña")) -> Mediana | U5: =IF(AND(N5="Estratégico",R5>=30%),"Alta",IF(OR(AND(N5="Estratégico",R5<30%),AND(N5="Potencial",R5>=30%)),"Media","Baja")) -> Media
A6: EX005 | B6: 46068 | C6: Comercial Azteca | D6: P005 | E6: México | F6: 500 | G6: 12.5 | H6: 8.7 | I6: Entregado | J6: =VLOOKUP(D6,Productos!$A$2:$D$6,2,FALSE()) -> Aceite de ajonjolí | K6: =VLOOKUP(D6,Productos!$A$2:$D$6,3,FALSE()) -> Aceites | L6: =VLOOKUP(E6,Mercados!$A$2:$D$7,2,FALSE()) -> Norteamérica | M6: =VLOOKUP(E6,Mercados!$A$2:$D$7,3,FALSE()) -> 0.08 | N6: =VLOOKUP(E6,Mercados!$A$2:$D$7,4,FALSE()) -> Potencial | O6: =F6*G6 -> 6250 | P6: =F6*H6 -> 4350 | Q6: =O6-P6 -> 1900 | R6: =Q6/O6 -> 0.304 | S6: =IF(R6>=30%,"Alta",IF(R6>=15%,"Media","Baja")) -> Alta | T6: =IF(O6>=10000,"Grande",IF(O6>=5000,"Mediana","Pequeña")) -> Mediana | U6: =IF(AND(N6="Estratégico",R6>=30%),"Alta",IF(OR(AND(N6="Estratégico",R6<30%),AND(N6="Potencial",R6>=30%)),"Media","Baja")) -> Media
A7: EX006 | B7: 46081 | C7: Global Foods | D7: P003 | E7: EE.UU. | F7: 1400 | G7: 4.8 | H7: 3.2 | I7: Entregado | J7: =VLOOKUP(D7,Productos!$A$2:$D$6,2,FALSE()) -> Miel natural | K7: =VLOOKUP(D7,Productos!$A$2:$D$6,3,FALSE()) -> Apícola | L7: =VLOOKUP(E7,Mercados!$A$2:$D$7,2,FALSE()) -> Norteamérica | M7: =VLOOKUP(E7,Mercados!$A$2:$D$7,3,FALSE()) -> 0.05 | N7: =VLOOKUP(E7,Mercados!$A$2:$D$7,4,FALSE()) -> Estratégico | O7: =F7*G7 -> 6720 | P7: =F7*H7 -> 4480 | Q7: =O7-P7 -> 2240 | R7: =Q7/O7 -> 0.33333333 | S7: =IF(R7>=30%,"Alta",IF(R7>=15%,"Media","Baja")) -> Alta | T7: =IF(O7>=10000,"Grande",IF(O7>=5000,"Mediana","Pequeña")) -> Mediana | U7: =IF(AND(N7="Estratégico",R7>=30%),"Alta",IF(OR(AND(N7="Estratégico",R7<30%),AND(N7="Potencial",R7>=30%)),"Media","Baja")) -> Alta
A8: EX007 | B8: 46089 | C8: Distribuidora Tica | D8: P001 | E8: Costa Rica | F8: 900 | G8: 6.5 | H8: 4.1 | I8: Embarcado | J8: =VLOOKUP(D8,Productos!$A$2:$D$6,2,FALSE()) -> Café especial | K8: =VLOOKUP(D8,Productos!$A$2:$D$6,3,FALSE()) -> Café | L8: =VLOOKUP(E8,Mercados!$A$2:$D$7,2,FALSE()) -> Centroamérica | M8: =VLOOKUP(E8,Mercados!$A$2:$D$7,3,FALSE()) -> 0.02 | N8: =VLOOKUP(E8,Mercados!$A$2:$D$7,4,FALSE()) -> Estratégico | O8: =F8*G8 -> 5850 | P8: =F8*H8 -> 3690 | Q8: =O8-P8 -> 2160 | R8: =Q8/O8 -> 0.36923077 | S8: =IF(R8>=30%,"Alta",IF(R8>=15%,"Media","Baja")) -> Alta | T8: =IF(O8>=10000,"Grande",IF(O8>=5000,"Mediana","Pequeña")) -> Mediana | U8: =IF(AND(N8="Estratégico",R8>=30%),"Alta",IF(OR(AND(N8="Estratégico",R8<30%),AND(N8="Potencial",R8>=30%)),"Media","Baja")) -> Alta
A9: EX008 | B9: 46099 | C9: Comercial Maya | D9: P004 | E9: Guatemala | F9: 750 | G9: 8.2 | H9: 5.9 | I9: Entregado | J9: =VLOOKUP(D9,Productos!$A$2:$D$6,2,FALSE()) -> Maní procesado | K9: =VLOOKUP(D9,Productos!$A$2:$D$6,3,FALSE()) -> Semillas | L9: =VLOOKUP(E9,Mercados!$A$2:$D$7,2,FALSE()) -> Centroamérica | M9: =VLOOKUP(E9,Mercados!$A$2:$D$7,3,FALSE()) -> 0.03 | N9: =VLOOKUP(E9,Mercados!$A$2:$D$7,4,FALSE()) -> Estratégico | O9: =F9*G9 -> 6150 | P9: =F9*H9 -> 4425 | Q9: =O9-P9 -> 1725 | R9: =Q9/O9 -> 0.2804878 | S9: =IF(R9>=30%,"Alta",IF(R9>=15%,"Media","Baja")) -> Media | T9: =IF(O9>=10000,"Grande",IF(O9>=5000,"Mediana","Pequeña")) -> Mediana | U9: =IF(AND(N9="Estratégico",R9>=30%),"Alta",IF(OR(AND(N9="Estratégico",R9<30%),AND(N9="Potencial",R9>=30%)),"Media","Baja")) -> Media
A10: EX009 | B10: 46106 | C10: Iberia Foods | D10: P005 | E10: España | F10: 600 | G10: 12.5 | H10: 8.7 | I10: Embarcado | J10: =VLOOKUP(D10,Productos!$A$2:$D$6,2,FALSE()) -> Aceite de ajonjolí | K10: =VLOOKUP(D10,Productos!$A$2:$D$6,3,FALSE()) -> Aceites | L10: =VLOOKUP(E10,Mercados!$A$2:$D$7,2,FALSE()) -> Europa | M10: =VLOOKUP(E10,Mercados!$A$2:$D$7,3,FALSE()) -> 0.1 | N10: =VLOOKUP(E10,Mercados!$A$2:$D$7,4,FALSE()) -> Potencial | O10: =F10*G10 -> 7500 | P10: =F10*H10 -> 5220 | Q10: =O10-P10 -> 2280 | R10: =Q10/O10 -> 0.304 | S10: =IF(R10>=30%,"Alta",IF(R10>=15%,"Media","Baja")) -> Alta | T10: =IF(O10>=10000,"Grande",IF(O10>=5000,"Mediana","Pequeña")) -> Mediana | U10: =IF(AND(N10="Estratégico",R10>=30%),"Alta",IF(OR(AND(N10="Estratégico",R10<30%),AND(N10="Potencial",R10>=30%)),"Media","Baja")) -> Media
A11: EX010 | B11: 46114 | C11: Comercial Azteca | D11: P002 | E11: México | F11: 1100 | G11: 7.1 | H11: 4.8 | I11: Entregado | J11: =VLOOKUP(D11,Productos!$A$2:$D$6,2,FALSE()) -> Cacao en grano | K11: =VLOOKUP(D11,Productos!$A$2:$D$6,3,FALSE()) -> Cacao | L11: =VLOOKUP(E11,Mercados!$A$2:$D$7,2,FALSE()) -> Norteamérica | M11: =VLOOKUP(E11,Mercados!$A$2:$D$7,3,FALSE()) -> 0.08 | N11: =VLOOKUP(E11,Mercados!$A$2:$D$7,4,FALSE()) -> Potencial | O11: =F11*G11 -> 7810 | P11: =F11*H11 -> 5280 | Q11: =O11-P11 -> 2530 | R11: =Q11/O11 -> 0.32394366 | S11: =IF(R11>=30%,"Alta",IF(R11>=15%,"Media","Baja")) -> Alta | T11: =IF(O11>=10000,"Grande",IF(O11>=5000,"Mediana","Pequeña")) -> Mediana | U11: =IF(AND(N11="Estratégico",R11>=30%),"Alta",IF(OR(AND(N11="Estratégico",R11<30%),AND(N11="Potencial",R11>=30%)),"Media","Baja")) -> Media
A12: EX011 | B12: 46122 | C12: Global Foods | D12: P004 | E12: EE.UU. | F12: 1300 | G12: 8.2 | H12: 5.9 | I12: Entregado | J12: =VLOOKUP(D12,Productos!$A$2:$D$6,2,FALSE()) -> Maní procesado | K12: =VLOOKUP(D12,Productos!$A$2:$D$6,3,FALSE()) -> Semillas | L12: =VLOOKUP(E12,Mercados!$A$2:$D$7,2,FALSE()) -> Norteamérica | M12: =VLOOKUP(E12,Mercados!$A$2:$D$7,3,FALSE()) -> 0.05 | N12: =VLOOKUP(E12,Mercados!$A$2:$D$7,4,FALSE()) -> Estratégico | O12: =F12*G12 -> 10660 | P12: =F12*H12 -> 7670 | Q12: =O12-P12 -> 2990 | R12: =Q12/O12 -> 0.2804878 | S12: =IF(R12>=30%,"Alta",IF(R12>=15%,"Media","Baja")) -> Media | T12: =IF(O12>=10000,"Grande",IF(O12>=5000,"Mediana","Pequeña")) -> Grande | U12: =IF(AND(N12="Estratégico",R12>=30%),"Alta",IF(OR(AND(N12="Estratégico",R12<30%),AND(N12="Potencial",R12>=30%)),"Media","Baja")) -> Media
A13: EX012 | B13: 46130 | C13: Comercial Maya | D13: P001 | E13: Guatemala | F13: 700 | G13: 6.5 | H13: 4.1 | I13: Pendiente | J13: =VLOOKUP(D13,Productos!$A$2:$D$6,2,FALSE()) -> Café especial | K13: =VLOOKUP(D13,Productos!$A$2:$D$6,3,FALSE()) -> Café | L13: =VLOOKUP(E13,Mercados!$A$2:$D$7,2,FALSE()) -> Centroamérica | M13: =VLOOKUP(E13,Mercados!$A$2:$D$7,3,FALSE()) -> 0.03 | N13: =VLOOKUP(E13,Mercados!$A$2:$D$7,4,FALSE()) -> Estratégico | O13: =F13*G13 -> 4550 | P13: =F13*H13 -> 2870 | Q13: =O13-P13 -> 1680 | R13: =Q13/O13 -> 0.36923077 | S13: =IF(R13>=30%,"Alta",IF(R13>=15%,"Media","Baja")) -> Alta | T13: =IF(O13>=10000,"Grande",IF(O13>=5000,"Mediana","Pequeña")) -> Pequeña | U13: =IF(AND(N13="Estratégico",R13>=30%),"Alta",IF(OR(AND(N13="Estratégico",R13<30%),AND(N13="Potencial",R13>=30%)),"Media","Baja")) -> Alta
... A101: EX100 | B101: 46150 | C101: Comercial Azteca | D101: P001 | E101: México | F101: 1170 | G101: 6.5 | H101: 4.1 | I101: Entregado | J101: =VLOOKUP(D101,Productos!$A$2:$D$6,2,FALSE()) -> Café especial | K101: =VLOOKUP(D101,Productos!$A$2:$D$6,3,FALSE()) -> Café | L101: =VLOOKUP(E101,Mercados!$A$2:$D$7,2,FALSE()) -> Norteamérica | M101: =VLOOKUP(E101,Mercados!$A$2:$D$7,3,FALSE()) -> 0.08 | N101: =VLOOKUP(E101,Mercados!$A$2:$D$7,4,FALSE()) -> Potencial | O101: =F101*G101 -> 7605 | P101: =F101*H101 -> 4797 | Q101: =O101-P101 -> 2808 | R101: =Q101/O101 -> 0.36923077 | S101: =IF(R101>=30%,"Alta",IF(R101>=15%,"Media","Baja")) -> Alta | T101: =IF(O101>=10000,"Grande",IF(O101>=5000,"Mediana","Pequeña")) -> Mediana | U101: =IF(AND(N101="Estratégico",R101>=30%),"Alta",IF(OR(AND(N101="Estratégico",R101<30%),AND(N101="Potencial",R101>=30%)),"Media","Baja")) -> Media

Sheet Productos
A1: Código | B1: Producto | C1: Categoría | D1: Unidad de Medida
A2: P001 | B2: Café especial | C2: Café | D2: Kg
A3: P002 | B3: Cacao en grano | C3: Cacao | D3: Kg
A4: P003 | B4: Miel natural | C4: Apícola | D4: Kg
A5: P004 | B5: Maní procesado | C5: Semillas | D5: Kg
A6: P005 | B6: Aceite de ajonjolí | C6: Aceites | D6: Litro

Sheet Mercados
A1: País | B1: Región | C1: Arancel % | D1: Clasificación
A2: EE.UU. | B2: Norteamérica | C2: 0.05 | D2: Estratégico
A3: México | B3: Norteamérica | C3: 0.08 | D3: Potencial
A4: Guatemala | B4: Centroamérica | C4: 0.03 | D4: Estratégico
A5: Costa Rica | B5: Centroamérica | C5: 0.02 | D5: Estratégico
A6: El Salvador | B6: Centroamérica | C6: 0.02 | D6: Potencial
A7: España | B7: Europa | C7: 0.1 | D7: Potencial

Sheet Análisis
A1: NicaExport Trading, S.A. — Análisis empresarial
A3: Operaciones | B3: =COUNTA(Operaciones!A2:A101) -> 100 | G3: Funciones condicionales
A4: Pendientes | B4: =COUNTIF(Operaciones!I2:I101,"Pendiente") -> 15 | G4: Operaciones EE.UU. | H4: =COUNTIF(Operaciones!E2:E101,"EE.UU.") -> 20
A5: Valor FOB | B5: =SUM(Operaciones!O2:O101) -> 658265 | G5: Operaciones pendientes | H5: =COUNTIF(Operaciones!I2:I101,"Pendiente") -> 15
A6: Costo total | B6: =SUM(Operaciones!P2:P101) -> 444193 | G6: FOB México | H6: =SUMIF(Operaciones!E2:E101,"México",Operaciones!O2:O101) -> 120313
A7: Utilidad | B7: =SUM(Operaciones!Q2:Q101) -> 214072 | G7: Unidades Guatemala | H7: =SUMIF(Operaciones!E2:E101,"Guatemala",Operaciones!F2:F101) -> 17130
A8: Margen global | B8: =SUM(Operaciones!Q2:Q101)/SUM(Operaciones!O2:O101) -> 0.32520641 | G8: FOB Café especial EE.UU. | H8: =SUMIFS(Operaciones!O2:O101,Operaciones!J2:J101,"Café especial",Operaciones!E2:E101,"EE.UU.") -> 52390
A9: Rentabilidad alta | B9: =COUNTIF(Operaciones!S2:S101,"Alta") -> 82 | G9: Utilidad Centroamérica entregada | H9: =SUMIFS(Operaciones!Q2:Q101,Operaciones!L2:L101,"Centroamérica",Operaciones!I2:I101,"Entregado") -> 33348
A10: Prioridad alta | B10: =COUNTIF(Operaciones!U2:U101,"Alta") -> 48
A13: País | B13: Operaciones | C13: Unidades | D13: Valor FOB | E13: Utilidad | F13: Margen
A14: Guatemala | B14: =COUNTIF(Operaciones!E$2:E$101,A14) -> 20 | C14: =SUMIF(Operaciones!E$2:E$101,A14,Operaciones!F$2:F$101) -> 17130 | D14: =SUMIF(Operaciones!E$2:E$101,A14,Operaciones!O$2:O$101) -> 119335 | E14: =SUMIF(Operaciones!E$2:E$101,A14,Operaciones!Q$2:Q$101) -> 38912 | F14: =E14/D14 -> 0.32607366
A15: EE.UU. | B15: =COUNTIF(Operaciones!E$2:E$101,A15) -> 20 | C15: =SUMIF(Operaciones!E$2:E$101,A15,Operaciones!F$2:F$101) -> 24560 | D15: =SUMIF(Operaciones!E$2:E$101,A15,Operaciones!O$2:O$101) -> 168745 | E15: =SUMIF(Operaciones!E$2:E$101,A15,Operaciones!Q$2:Q$101) -> 55601 | F15: =E15/D15 -> 0.32949717
A16: Costa Rica | B16: =COUNTIF(Operaciones!E$2:E$101,A16) -> 20 | C16: =SUMIF(Operaciones!E$2:E$101,A16,Operaciones!F$2:F$101) -> 15590 | D16: =SUMIF(Operaciones!E$2:E$101,A16,Operaciones!O$2:O$101) -> 113544 | E16: =SUMIF(Operaciones!E$2:E$101,A16,Operaciones!Q$2:Q$101) -> 36329 | F16: =E16/D16 -> 0.31995526
A17: España | B17: =COUNTIF(Operaciones!E$2:E$101,A17) -> 20 | C17: =SUMIF(Operaciones!E$2:E$101,A17,Operaciones!F$2:F$101) -> 18900 | D17: =SUMIF(Operaciones!E$2:E$101,A17,Operaciones!O$2:O$101) -> 136328 | E17: =SUMIF(Operaciones!E$2:E$101,A17,Operaciones!Q$2:Q$101) -> 43648 | F17: =E17/D17 -> 0.320169
A18: México | B18: =COUNTIF(Operaciones!E$2:E$101,A18) -> 20 | C18: =SUMIF(Operaciones!E$2:E$101,A18,Operaciones!F$2:F$101) -> 15870 | D18: =SUMIF(Operaciones!E$2:E$101,A18,Operaciones!O$2:O$101) -> 120313 | E18: =SUMIF(Operaciones!E$2:E$101,A18,Operaciones!Q$2:Q$101) -> 39582 | F18: =E18/D18 -> 0.32899188
A21: Producto | B21: Unidades | C21: Valor FOB | D21: Utilidad | E21: Margen
A22: Café especial | B22: =SUMIF(Operaciones!J$2:J$101,A22,Operaciones!F$2:F$101) -> 26180 | C22: =SUMIF(Operaciones!J$2:J$101,A22,Operaciones!O$2:O$101) -> 170170 | D22: =SUMIF(Operaciones!J$2:J$101,A22,Operaciones!Q$2:Q$101) -> 62832 | E22: =D22/C22 -> 0.36923077
A23: Miel natural | B23: =SUMIF(Operaciones!J$2:J$101,A23,Operaciones!F$2:F$101) -> 24180 | C23: =SUMIF(Operaciones!J$2:J$101,A23,Operaciones!O$2:O$101) -> 116064 | D23: =SUMIF(Operaciones!J$2:J$101,A23,Operaciones!Q$2:Q$101) -> 38688 | E23: =D23/C23 -> 0.33333333
A24: Aceite de ajonjolí | B24: =SUMIF(Operaciones!J$2:J$101,A24,Operaciones!F$2:F$101) -> 11110 | C24: =SUMIF(Operaciones!J$2:J$101,A24,Operaciones!O$2:O$101) -> 138875 | D24: =SUMIF(Operaciones!J$2:J$101,A24,Operaciones!Q$2:Q$101) -> 42218 | E24: =D24/C24 -> 0.304
A25: Semillas de chía | B25: =SUMIF(Operaciones!J$2:J$101,A25,Operaciones!F$2:F$101) -> 0 | C25: =SUMIF(Operaciones!J$2:J$101,A25,Operaciones!O$2:O$101) -> 0 | D25: =SUMIF(Operaciones!J$2:J$101,A25,Operaciones!Q$2:Q$101) -> 0 | E25: =D25/C25 -> #DIV/0!
A26: Cacao orgánico | B26: =SUMIF(Operaciones!J$2:J$101,A26,Operaciones!F$2:F$101) -> 0 | C26: =SUMIF(Operaciones!J$2:J$101,A26,Operaciones!O$2:O$101) -> 0 | D26: =SUMIF(Operaciones!J$2:J$101,A26,Operaciones!Q$2:Q$101) -> 0 | E26: =D26/C26 -> #DIV/0!

Sheet Gráficos
A1: Gráficos — NicaExport Trading, S.A.
A3: País | B3: Valor FOB
A4: Guatemala | B4: =Análisis!D14 -> 119335
A5: EE.UU. | B5: =Análisis!D15 -> 168745
A6: Costa Rica | B6: =Análisis!D16 -> 113544
A7: España | B7: =Análisis!D17 -> 136328
A8: México | B8: =Análisis!D18 -> 120313
A11: Producto | B11: Utilidad
A12: Café especial | B12: =Análisis!D22 -> 62832
A13: Miel natural | B13: =Análisis!D23 -> 38688
A14: Aceite de ajonjolí | B14: =Análisis!D24 -> 42218
A15: Semillas de chía | B15: =Análisis!D25 -> 0
A16: Cacao orgánico | B16: =Análisis!D26 -> 0
A20: Región | B20: Valor FOB
A21: Centroamérica | B21: =SUMIF(Operaciones!L$2:L$101,A21,Operaciones!O$2:O$101) -> 232879
A22: Norteamérica | B22: =SUMIF(Operaciones!L$2:L$101,A22,Operaciones!O$2:O$101) -> 289058
A23: Europa | B23: =SUMIF(Operaciones!L$2:L$101,A23,Operaciones!O$2:O$101) -> 136328
